django_describer/__init__.py
django_describer/actions.py
django_describer/datatypes.py
django_describer/describers.py
django_describer/permissions.py
django_describer/utils.py
django_describer/adapters/__init__.py
django_describer/adapters/base.py
django_describer/adapters/utils.py
django_describer/adapters/graphql/__init__.py
django_describer/adapters/graphql/converter.py
django_describer/adapters/graphql/fields.py
django_describer/adapters/graphql/main.py
django_describer/adapters/graphql/modifying.py
django_describer/adapters/graphql/pagination.py
django_describer/adapters/graphql/retrieving.py
django_describer-0.0.24.dist-info/LICENSE
django_describer-0.0.24.dist-info/METADATA
django_describer-0.0.24.dist-info/WHEEL
django_describer-0.0.24.dist-info/top_level.txt
django_describer-0.0.24.dist-info/RECORD
